{
  "locale": "en",
  "metadata": {
    "title": "心行者 Mindhikers",
    "description": "MindHikers researches complex questions, creates clear expression, and experiments with productized creative workflows."
  },
  "navigation": {
    "brand": "心行者 Mindhikers",
    "links": [
      {
        "href": "/en#about",
        "label": "About"
      },
      {
        "href": "/en#product",
        "label": "Product"
      },
      {
        "href": "/en#blog",
        "label": "Blog"
      },
      {
        "href": "/en#contact",
        "label": "Contact"
      }
    ],
    "switchLanguage": {
      "href": "/",
      "label": "中文"
    }
  },
  "hero": {
    "eyebrow": "MindHikers",
    "title": "MindHikers",
    "description": "Research. Create. Productize.",
    "primaryAction": {
      "href": "#product",
      "label": "Explore Products"
    },
    "secondaryAction": {
      "href": "/blog",
      "label": "Read Blog"
    },
    "highlights": [
      "Research complex questions",
      "Create clear expression",
      "Productize workflows"
    ],
    "panelTitle": "Quick links",
    "quickLinks": [
      {
        "label": "Golden Crucible",
        "href": "/en/golden-crucible",
        "tag": "Product"
      },
      {
        "label": "Carbon-Silicon Evolution",
        "href": "/blog",
        "tag": "Writing"
      }
    ]
  },
  "about": {
    "title": "About",
    "intro": "MindHikers is a one-person studio doing two things:",
    "paragraphs": [
      "Content: deep-dive research and storytelling on YouTube and Bilibili for intellectually curious audiences navigating the AI era.",
      "Products: turning creative workflows and research methods into tools. Built for ourselves first, then shared."
    ],
    "notes": [
      "In an age where AI writes, draws, and thinks for you, the scarcest human quality is knowing who you are.",
      "Pain is the standard of truth; friction is where growth happens.",
      "Anchor first, then climb."
    ]
  },
  "product": {
    "title": "Product",
    "description": "A product experiment around research, writing, expression, and creator workflows.",
    "headline": "The Crucible",
    "featured": {
      "eyebrow": "Featured release",
      "title": "The Crucible",
      "description": "A product experiment around research, writing, expression, and creator workflows. Currently open: AI-assisted deep writing workflow, knowledge management templates, and a creator productivity toolkit.",
      "href": "/en/golden-crucible",
      "ctaLabel": "Open product page",
      "meta": "Live now"
    },
    "items": [
      {
        "eyebrow": "Workflow",
        "title": "AI-assisted deep writing workflow",
        "description": "A reusable process for research, outlining, drafting, revision, and publishing."
      },
      {
        "eyebrow": "Templates",
        "title": "Knowledge management templates",
        "description": "Durable systems for collecting, reviewing, and extending long-term research threads."
      },
      {
        "eyebrow": "Toolkit",
        "title": "Creator productivity toolkit",
        "description": "Lightweight tools for topics, expression, source management, and publishing rhythm."
      }
    ]
  },
  "blog": {
    "title": "Content flow",
    "description": "Three Carbon-Silicon Evolution essays are live, exploring education, embodied experience, and moral growth in the AI age.",
    "headline": "Carbon-Silicon Evolution",
    "cta": {
      "href": "/blog",
      "label": "Browse all posts"
    },
    "emptyLabel": "The first wave of writing is still being curated.",
    "readArticleLabel": "Read article"
  },
  "contact": {
    "title": "Contact",
    "description": "We welcome content partnerships, product collaborations, and thoughtful internet projects.",
    "headline": "Have a collaboration idea, or just want to chat?",
    "emailLabel": "Email",
    "email": "hello@mindhikers.com",
    "locationLabel": "Base",
    "location": "Shanghai / Remote",
    "availabilityLabel": "Open to",
    "availability": "Content partnerships · Product collaborations · Thoughtful internet projects",
    "links": [
      {
        "href": "mailto:hello@mindhikers.com",
        "label": "Send email",
        "note": "hello@mindhikers.com"
      },
      {
        "href": "/",
        "label": "Chinese home",
        "note": "Switch back to the Chinese entry"
      },
      {
        "href": "/blog",
        "label": "Recent writing",
        "note": "Start with the blog to understand the practice"
      }
    ]
  },
  "productDetail": {
    "eyebrow": "Featured Product",
    "title": "Golden Crucible",
    "summary": "Golden Crucible is the first public product entry under 心行者 Mindhikers, designed to hold early experiments around research, expression, and creator workflows.",
    "bullets": [
      "Organize research threads into durable topic assets",
      "Turn expression work into reusable scripts and structures",
      "Gradually shape creator workflows into productized tools"
    ],
    "stageLabel": "Current stage",
    "stageValue": "The branded entry page is live first. More product detail and richer assets will follow.",
    "returnHome": {
      "href": "/en",
      "label": "Back to homepage"
    },
    "switchLanguage": {
      "href": "/golden-crucible",
      "label": "查看中文版"
    }
  }
}
